{"name":"build-javascript","namedChunkGroups":{"polyfill":{"name":"polyfill","assets":[{"name":"webpack-runtime-428b881cfa07369d23d2.js","size":4451},{"name":"polyfill-4718f0fec20e0d09d7f5.js","size":85862}],"filteredAssets":0,"assetsSize":90313,"filteredAuxiliaryAssets":2,"auxiliaryAssetsSize":225814},"app":{"name":"app","assets":[{"name":"webpack-runtime-428b881cfa07369d23d2.js","size":4451},{"name":"framework-54a02ad02f23896e401c.js","size":140566},{"name":"app-ac02fbba7f74c533ffbc.js","size":65865}],"filteredAssets":0,"assetsSize":210882,"filteredAuxiliaryAssets":3,"auxiliaryAssetsSize":629225},"component---src-pages-404-js":{"name":"component---src-pages-404-js","assets":[{"name":"styles.5935312d2683c5e8fc5f.css","size":3037},{"name":"commons-61f6e4cd8cfa41527fc2.js","size":17308},{"name":"component---src-pages-404-js-99560834a3cdc50d7cdf.js","size":484}],"filteredAssets":0,"assetsSize":20829,"filteredAuxiliaryAssets":2,"auxiliaryAssetsSize":71451},"component---src-pages-about-js":{"name":"component---src-pages-about-js","assets":[{"name":"styles.5935312d2683c5e8fc5f.css","size":3037},{"name":"commons-61f6e4cd8cfa41527fc2.js","size":17308},{"name":"component---src-pages-about-js-6a6097ce5d0c0b8fd6f1.js","size":462}],"filteredAssets":0,"assetsSize":20807,"filteredAuxiliaryAssets":2,"auxiliaryAssetsSize":71424},"component---src-pages-index-js":{"name":"component---src-pages-index-js","assets":[{"name":"styles.5935312d2683c5e8fc5f.css","size":3037},{"name":"commons-61f6e4cd8cfa41527fc2.js","size":17308},{"name":"component---src-pages-index-js-bd1fbbc89f88fd55446b.js","size":399}],"filteredAssets":0,"assetsSize":20744,"filteredAuxiliaryAssets":2,"auxiliaryAssetsSize":71384}},"assetsByChunkName":{"polyfill":["webpack-runtime-428b881cfa07369d23d2.js","polyfill-4718f0fec20e0d09d7f5.js"],"app":["webpack-runtime-428b881cfa07369d23d2.js","framework-54a02ad02f23896e401c.js","app-ac02fbba7f74c533ffbc.js"],"component---src-pages-404-js":["styles.5935312d2683c5e8fc5f.css","commons-61f6e4cd8cfa41527fc2.js","component---src-pages-404-js-99560834a3cdc50d7cdf.js"],"component---src-pages-about-js":["styles.5935312d2683c5e8fc5f.css","commons-61f6e4cd8cfa41527fc2.js","component---src-pages-about-js-6a6097ce5d0c0b8fd6f1.js"],"component---src-pages-index-js":["styles.5935312d2683c5e8fc5f.css","commons-61f6e4cd8cfa41527fc2.js","component---src-pages-index-js-bd1fbbc89f88fd55446b.js"]},"childAssetsByChunkName":{}}